{
   "tasks":[
    {
        "id": 1,
        "text": "Terminar primero modulo de Angular",
        "day": "Agosto 5 a las 12:00",
        "reminder": true
    },
    {
        "id": 2,
        "text": "Hacer compras para la semana",
        "day": "Agosto 5 a las 17:00",
        "reminder": true
    },
    {
        "id": 3,
        "text": "Investigar sobre Booststrap",
        "day": "Agosto 5 a las 12:00",
        "reminder": false
    },
    {
        "id": 4,
        "text": "Leer mi libro favorito",
        "day": "Abril 8 a las 12:00",
        "reminder": true
    }
   ] 
}